{
  "name": "hvl-ccb",
  "version": "0.19.2",
  "summary": "Python common code base to control research devices, in particular, as used in Christian Franck's High Voltage Lab (HVL), D-ITET, ETH Zurich",
  "author": "Pit Bechtold, Fabian Bill, Alise Chachereau, Maria Del, Joseph Engelbrecht, Raphael Faerber, David Graber, Chi-Ching Hsu, Henning Janssen, Henrik Menne, Luca Nembrini, Mikołaj Rybiński, Ruben Stadler, David Taylor, Hanut Vemulapalli",
  "license": null,
  "home_page": null,
  "download_filename": "hvl_ccb-0.19.2.tar.gz",
  "download_time": "2026-03-01T09:53:42.515240",
  "package_url": "https://pypi.org/project/hvl-ccb/"
}